py_portfolio_index/__init__.py
py_portfolio_index/analytics.py
py_portfolio_index/common.py
py_portfolio_index/config.py
py_portfolio_index/constants.py
py_portfolio_index/enums.py
py_portfolio_index/exceptions.py
py_portfolio_index/models.py
py_portfolio_index/operators.py
py_portfolio_index/py.typed
py_portfolio_index/bin/__init__.py
py_portfolio_index/bin/cached_ticker_list.csv
py_portfolio_index/bin/stock_info.json
py_portfolio_index/bin/indexes/__init__.py
py_portfolio_index/bin/indexes/basic_materials.json
py_portfolio_index/bin/indexes/blank.json
py_portfolio_index/bin/indexes/blended_world_60_40.json
py_portfolio_index/bin/indexes/consumer_discretionary.json
py_portfolio_index/bin/indexes/consumer_staples.json
py_portfolio_index/bin/indexes/core_cap.json
py_portfolio_index/bin/indexes/core_growth.json
py_portfolio_index/bin/indexes/core_value.json
py_portfolio_index/bin/indexes/crsp_iss_large_esg.json
py_portfolio_index/bin/indexes/crsp_iss_large_esg_industry_balanced.json
py_portfolio_index/bin/indexes/crsp_iss_large_esg_industry_balanced_remainder.json
py_portfolio_index/bin/indexes/crsp_iss_large_esg_non-prime.json
py_portfolio_index/bin/indexes/crsp_iss_large_esg_prime.json
py_portfolio_index/bin/indexes/crsp_iss_large_esg_remainder.json
py_portfolio_index/bin/indexes/energy.json
py_portfolio_index/bin/indexes/eu_index.json
py_portfolio_index/bin/indexes/financials.json
py_portfolio_index/bin/indexes/health_care.json
py_portfolio_index/bin/indexes/healthcare.json
py_portfolio_index/bin/indexes/industrials.json
py_portfolio_index/bin/indexes/inventory.py
py_portfolio_index/bin/indexes/large_cap.json
py_portfolio_index/bin/indexes/large_growth.json
py_portfolio_index/bin/indexes/large_value.json
py_portfolio_index/bin/indexes/materials.json
py_portfolio_index/bin/indexes/media_&_communications.json
py_portfolio_index/bin/indexes/mega_cap.json
py_portfolio_index/bin/indexes/mega_growth.json
py_portfolio_index/bin/indexes/mega_value.json
py_portfolio_index-0.1.49.dist-info/licenses/LICENSE.txt
py_portfolio_index-0.1.49.dist-info/METADATA
py_portfolio_index-0.1.49.dist-info/WHEEL
py_portfolio_index-0.1.49.dist-info/top_level.txt
py_portfolio_index-0.1.49.dist-info/RECORD
