Metadata-Version: 2.4
Name: py-portfolio-index
Version: 0.1.49
Summary: Build index portfolios.
Home-page: 
Author: 
Classifier: Programming Language :: Python
Classifier: Programming Language :: Python :: 3
Classifier: Programming Language :: Python :: 3.9
Classifier: Programming Language :: Python :: 3.10
Classifier: Programming Language :: Python :: 3.11
License-File: LICENSE.txt
Requires-Dist: pandas
Requires-Dist: pydantic
Requires-Dist: platformdirs
Requires-Dist: pytrilogy
Provides-Extra: alpaca
Requires-Dist: alpaca-py; extra == "alpaca"
Provides-Extra: robinhood
Requires-Dist: robin-stocks; extra == "robinhood"
Provides-Extra: webull
Requires-Dist: webull; extra == "webull"
Provides-Extra: schwab
Requires-Dist: schwab-py; extra == "schwab"
Provides-Extra: moomoo
Requires-Dist: moomoo-api; extra == "moomoo"
Dynamic: classifier
Dynamic: description
Dynamic: description-content-type
Dynamic: license-file
Dynamic: provides-extra
Dynamic: requires-dist
Dynamic: summary
